pyAuthManager/__init__.py
pyAuthManager/aws/__init__.py
pyAuthManager/aws/code.py
pyAuthManager/aws/signin.py
pyAuthManager/aws/signup.py
pyAuthManager/aws/validation.py
pyAuthManager/azure/__init__.py
pyAuthManager/funcs.py
pyAuthManager/gcp/__init__.py
pyAuthManager/gcp/code.py
pyAuthManager/gcp/signin.py
pyAuthManager/gcp/signup.py
pyAuthManager/gcp/validation.py
pyAuthManager/init.py
pyAuthManager/libs/__init__.py
pyAuthManager/libs/response.py
pyauthmanager-0.1.4.3.dist-info/METADATA
pyauthmanager-0.1.4.3.dist-info/WHEEL
pyauthmanager-0.1.4.3.dist-info/RECORD
