Metadata-Version: 2.1
Name: pyauthmanager
Version: 0.1.4.3
Summary: 
License: Free
Author: Touni Atchadé
Author-email: romuald.atchade@tounilab.com>, Hervé Martin <hervefranciscomartin@gmail.com
Requires-Python: >=3.10,<4.0
Classifier: License :: Other/Proprietary License
Classifier: Programming Language :: Python :: 3
Classifier: Programming Language :: Python :: 3.10
Classifier: Programming Language :: Python :: 3.11
Requires-Dist: boto3 (>=1.26.32,<2.0.0)
Requires-Dist: botocore (>=1.29.32,<2.0.0)
Requires-Dist: firebase-admin (>=6.0.1,<7.0.0)
Requires-Dist: python-decouple (>=3.6,<4.0)
Requires-Dist: python-jose (>=3.3.0,<4.0.0)
Requires-Dist: requests (>=2.28.1,<3.0.0)
